rightsignature/RightSignature.py
rightsignature/__init__.py
rightsignature-1.2.dist-info/LICENSE.txt
rightsignature-1.2.dist-info/METADATA
rightsignature-1.2.dist-info/WHEEL
rightsignature-1.2.dist-info/top_level.txt
rightsignature-1.2.dist-info/RECORD
