Metadata-Version: 2.1
Name: rightsignature
Version: 1.2
Summary: RightSignature API written in python
Home-page: https://github.com/kaiseranton/RightSignature
Author: Anton Kaiser
Author-email: kaiser@kaiser.ovh
License: UNKNOWN
Platform: UNKNOWN
Classifier: Programming Language :: Python :: 3
Classifier: License :: OSI Approved :: MIT License
Classifier: Operating System :: OS Independent
Requires-Dist: requests (>=2.21.0)
Requires-Dist: datetime (>=4.3)
